rahkaran_api/__init__.py
rahkaran_api/client.py
rahkaran_api/config.py
rahkaran_api/exceptions.py
rahkaranpythonapi-0.1.1.dist-info/licenses/LICENSE
rahkaranpythonapi-0.1.1.dist-info/METADATA
rahkaranpythonapi-0.1.1.dist-info/WHEEL
rahkaranpythonapi-0.1.1.dist-info/top_level.txt
rahkaranpythonapi-0.1.1.dist-info/RECORD
